ingestor/.python-version
ingestor/Dockerfile
ingestor/__init__.py
ingestor/bq/__init__.py
ingestor/bq/load.py
ingestor/bq/options.py
ingestor/bq/schemas/__init__.py
ingestor/bq/schemas/author.json
ingestor/bq/schemas/providers.py
ingestor/cli.py
ingestor/common_options.py
ingestor/exec.py
ingestor/gcs/__init__.py
ingestor/gcs/ingestion.py
ingestor/gcs/options.py
ingestor/gcs/schemas/__init__.py
ingestor/gcs/schemas/author.avsc
ingestor/gcs/schemas/providers.py
ingestor/ingest.py
ingestor/load.py
ingestor-0.0.3.dist-info/WHEEL
ingestor-0.0.3.dist-info/entry_points.txt
ingestor-0.0.3.dist-info/METADATA
ingestor-0.0.3.dist-info/RECORD
