Metadata-Version: 2.1
Name: ingestor
Version: 0.0.3
Summary: Apache Beam pipeline that ingests data from a PostgreSQL and writes it to GCS.
Author: Roman Dryndik
Requires-Python: >=3.9
Classifier: Programming Language :: Python :: 3
Classifier: Programming Language :: Python :: 3.9
Classifier: Programming Language :: Python :: 3.10
Classifier: Programming Language :: Python :: 3.11
Requires-Dist: apache-beam[gcp] (==2.47.0)
Requires-Dist: avro (>=1.11.1,<2.0.0)
Requires-Dist: beam-nuggets (>=0.18.1,<0.19.0)
Requires-Dist: beam-postgres (>=0.3.2,<0.4.0)
Requires-Dist: click (>=8.1.3,<9.0.0)
Requires-Dist: ipdb (>=0.13.13,<0.14.0)
Requires-Dist: psycopg2-binary (>=2.9.6,<3.0.0)
